Workbook

Sheet 4th netflix_titles
A1: show_id | B1: type | C1: Title | D1: director | E1: cast | F1: country | G1: date_added | H1: release_year | I1: rating | J1: duration | K1: Duration_Number | L1: Duration_Type | M1: listed_in | N1: description
A2: s1 | B2: Movie | C2: =TRIM('4th netflix_titles'!$C2) -> Dick Johnson Is Dead | D2: =TRIM(C2) -> Kirsten Johnson | E2: =TRIM(D2) -> Not Available | F2: =TRIM(E2) -> United States | G2: September 25, 2021 | H2: 2020 | I2: PG-13 | J2: 90 min | K2: =LEFT(J2,FIND(" ",J2)-1) -> 90 | L2: =RIGHT(J2,LEN(J2)-FIND(" ",J2)) -> min | M2: Documentaries | N2: =TRIM(M2) -> Documentaries
A3: s2 | B3: TV Show | C3: =TRIM('4th netflix_titles'!$C3) -> Blood & Water | D3: =TRIM(C3) -> UNKNOWN | E3: =TRIM(D3) -> Ama Qamata, Khosi Ngema, Gail Mabalane, Thabang Molaba, Dillon Windvogel, Natasha Thahane, Arno Greeff, Xolile Tshabalala, Getmore Sithole, Cindy Mahlangu, Ryle De Morny, Greteli Fincham, Sello Maake Ka-Ncube, Odwa Gwanya, Mekaila Mathys, Sandi Schultz, Duane Williams, Shamilla Miller, Patrick Mofokeng | F3: =TRIM(E3) -> South Africa | G3: September 24, 2021 | H3: 2021 | I3: TV-MA | J3: 2 Seasons | K3: =LEFT(J3,FIND(" ",J3)-1) -> 2 | L3: =RIGHT(J3,LEN(J3)-FIND(" ",J3)) -> Seasons | M3: International TV Shows, TV Dramas, TV Mysteries | N3: =TRIM(M3) -> International TV Shows, TV Dramas, TV Mysteries
A4: s3 | B4: TV Show | C4: =TRIM('4th netflix_titles'!$C4) -> Ganglands | D4: =TRIM(C4) -> Julien Leclercq | E4: =TRIM(D4) -> Sami Bouajila, Tracy Gotoas, Samuel Jouy, Nabiha Akkari, Sofia Lesaffre, Salim Kechiouche, Noureddine Farihi, Geert Van Rampelberg, Bakary Diombera | F4: =TRIM(E4) -> UNKNOWN | G4: September 24, 2021 | H4: 2021 | I4: TV-MA | J4: 1 Season | K4: =LEFT(J4,FIND(" ",J4)-1) -> 1 | L4: =RIGHT(J4,LEN(J4)-FIND(" ",J4)) -> Season | M4: Crime TV Shows, International TV Shows, TV Action & Adventure | N4: =TRIM(M4) -> Crime TV Shows, International TV Shows, TV Action & Adventure
A5: s4 | B5: TV Show | C5: =TRIM('4th netflix_titles'!$C5) -> Jailbirds New Orleans | D5: =TRIM(C5) -> UNKNOWN | E5: =TRIM(D5) -> Not Available | F5: =TRIM(E5) -> UNKNOWN | G5: September 24, 2021 | H5: 2021 | I5: TV-MA | J5: 1 Season | K5: =LEFT(J5,FIND(" ",J5)-1) -> 1 | L5: =RIGHT(J5,LEN(J5)-FIND(" ",J5)) -> Season | M5: Docuseries, Reality TV | N5: =TRIM(M5) -> Docuseries, Reality TV
A6: s5 | B6: TV Show | C6: =TRIM('4th netflix_titles'!$C6) -> Kota Factory | D6: =TRIM(C6) -> UNKNOWN | E6: =TRIM(D6) -> Mayur More, Jitendra Kumar, Ranjan Raj, Alam Khan, Ahsaas Channa, Revathi Pillai, Urvi Singh, Arun Kumar | F6: =TRIM(E6) -> India | G6: September 24, 2021 | H6: 2021 | I6: TV-MA | J6: 2 Seasons | K6: =LEFT(J6,FIND(" ",J6)-1) -> 2 | L6: =RIGHT(J6,LEN(J6)-FIND(" ",J6)) -> Seasons | M6: International TV Shows, Romantic TV Shows, TV Comedies | N6: =TRIM(M6) -> International TV Shows, Romantic TV Shows, TV Comedies
A7: s6 | B7: TV Show | C7: =TRIM('4th netflix_titles'!$C7) -> Midnight Mass | D7: =TRIM(C7) -> Mike Flanagan | E7: =TRIM(D7) -> Kate Siegel, Zach Gilford, Hamish Linklater, Henry Thomas, Kristin Lehman, Samantha Sloyan, Igby Rigney, Rahul Kohli, Annarah Cymone, Annabeth Gish, Alex Essoe, Rahul Abburi, Matt Biedel, Michael Trucco, Crystal Balint, Louis Oliver | F7: =TRIM(E7) -> UNKNOWN | G7: September 24, 2021 | H7: 2021 | I7: TV-MA | J7: 1 Season | K7: =LEFT(J7,FIND(" ",J7)-1) -> 1 | L7: =RIGHT(J7,LEN(J7)-FIND(" ",J7)) -> Season | M7: TV Dramas, TV Horror, TV Mysteries | N7: =TRIM(M7) -> TV Dramas, TV Horror, TV Mysteries
A8: s7 | B8: Movie | C8: =TRIM('4th netflix_titles'!$C8) -> My Little Pony: A New Generation | D8: =TRIM(C8) -> Robert Cullen, JosÃ© Luis Ucha | E8: =TRIM(D8) -> Vanessa Hudgens, Kimiko Glenn, James Marsden, Sofia Carson, Liza Koshy, Ken Jeong, Elizabeth Perkins, Jane Krakowski, Michael McKean, Phil LaMarr | F8: =TRIM(E8) -> UNKNOWN | G8: September 24, 2021 | H8: 2021 | I8: PG | J8: 91 min | K8: =LEFT(J8,FIND(" ",J8)-1) -> 91 | L8: =RIGHT(J8,LEN(J8)-FIND(" ",J8)) -> min | M8: Children & Family Movies | N8: =TRIM(M8) -> Children & Family Movies
A9: s8 | B9: Movie | C9: =TRIM('4th netflix_titles'!$C9) -> Sankofa | D9: =TRIM(C9) -> Haile Gerima | E9: =TRIM(D9) -> Kofi Ghanaba, Oyafunmike Ogunlano, Alexandra Duah, Nick Medley, Mutabaruka, Afemo Omilami, Reggie Carter, Mzuri | F9: =TRIM(E9) -> United States, Ghana, Burkina Faso, United Kingdom, Germany, Ethiopia | G9: September 24, 2021 | H9: 1993 | I9: TV-MA | J9: 125 min | K9: =LEFT(J9,FIND(" ",J9)-1) -> 125 | L9: =RIGHT(J9,LEN(J9)-FIND(" ",J9)) -> min | M9: Dramas, Independent Movies, International Movies | N9: =TRIM(M9) -> Dramas, Independent Movies, International Movies
A10: s9 | B10: TV Show | C10: =TRIM('4th netflix_titles'!$C10) -> The Great British Baking Show | D10: =TRIM(C10) -> Andy Devonshire | E10: =TRIM(D10) -> Mel Giedroyc, Sue Perkins, Mary Berry, Paul Hollywood | F10: =TRIM(E10) -> United Kingdom | G10: September 24, 2021 | H10: 2021 | I10: TV-14 | J10: 9 Seasons | K10: =LEFT(J10,FIND(" ",J10)-1) -> 9 | L10: =RIGHT(J10,LEN(J10)-FIND(" ",J10)) -> Seasons | M10: British TV Shows, Reality TV | N10: =TRIM(M10) -> British TV Shows, Reality TV
A11: s10 | B11: Movie | C11: =TRIM('4th netflix_titles'!$C11) -> The Starling | D11: =TRIM(C11) -> Theodore Melfi | E11: =TRIM(D11) -> Melissa McCarthy, Chris O'Dowd, Kevin Kline, Timothy Olyphant, Daveed Diggs, Skyler Gisondo, Laura Harrier, Rosalind Chao, Kimberly Quinn, Loretta Devine, Ravi Kapoor | F11: =TRIM(E11) -> United States | G11: September 24, 2021 | H11: 2021 | I11: PG-13 | J11: 104 min | K11: =LEFT(J11,FIND(" ",J11)-1) -> 104 | L11: =RIGHT(J11,LEN(J11)-FIND(" ",J11)) -> min | M11: Comedies, Dramas | N11: =TRIM(M11) -> Comedies, Dramas
A12: s11 | B12: TV Show | C12: =TRIM('4th netflix_titles'!$C12) -> Vendetta: Truth, Lies and The Mafia | D12: =TRIM(C12) -> UNKNOWN | E12: =TRIM(D12) -> Not Available | F12: =TRIM(E12) -> UNKNOWN | G12: September 24, 2021 | H12: 2021 | I12: TV-MA | J12: 1 Season | K12: =LEFT(J12,FIND(" ",J12)-1) -> 1 | L12: =RIGHT(J12,LEN(J12)-FIND(" ",J12)) -> Season | M12: Crime TV Shows, Docuseries, International TV Shows | N12: =TRIM(M12) -> Crime TV Shows, Docuseries, International TV Shows
A13: s12 | B13: TV Show | C13: =TRIM('4th netflix_titles'!$C13) -> Bangkok Breaking | D13: =TRIM(C13) -> Kongkiat Komesiri | E13: =TRIM(D13) -> Sukollawat Kanarot, Sushar Manaying, Pavarit Mongkolpisit, Sahajak Boonthanakit, Suthipongse Thatphithakkul, Bhasaworn Bawronkirati, Daweerit Chullasapya, Waratthaya Wongchayaporn, Kittiphoom Wongpentak, Abhicha Thanachanun, Nophand Boonyai, Kittipong Khamsat, Arisara Wongchalee, Jaytiya Naiwattanakul, Pantipa Arunwattanachai, Panupan Jantanawong, Kungtap Saelim, Phumphat Chartsuriyakiat, Issara Veranitinunt, Keerati Sivakuae, Panjai Sirisuwan, Supranee Charoenpol, Suda Chuenban, Visaka Banhansupavat, Pitchatorn Santinatornkul | F13: =TRIM(E13) -> UNKNOWN | G13: September 23, 2021 | H13: 2021 | I13: TV-MA | J13: 1 Season | K13: =LEFT(J13,FIND(" ",J13)-1) -> 1 | L13: =RIGHT(J13,LEN(J13)-FIND(" ",J13)) -> Season | M13: Crime TV Shows, International TV Shows, TV Action & Adventure | N13: =TRIM(M13) -> Crime TV Shows, International TV Shows, TV Action & Adventure
... A6067: s6066 | B6067: Movie | C6067: =TRIM('4th netflix_titles'!$C6067) -> A Wrinkle in Time | D6067: =TRIM(C6067) -> Ava DuVernay | E6067: =TRIM(D6067) -> Storm Reid, Oprah Winfrey, Reese Witherspoon, Mindy Kaling, Deric McCabe, Levi Miller, Chris Pine, Gugu Mbatha-Raw, Zach Galifianakis, Michael PeÃ±a, Bellamy Young, AndrÃ© Holland, Will McCormack, Rowan Blanchard, Daniel MacPherson | F6067: =TRIM(E6067) -> United States | G6067: September 25, 2018 | H6067: 2018 | I6067: PG | J6067: 110 min | K6067: =LEFT(J6067,FIND(" ",J6067)-1) -> 110 | L6067: =RIGHT(J6067,LEN(J6067)-FIND(" ",J6067)) -> min | M6067: Children & Family Movies | N6067: =TRIM(M6067) -> Children & Family Movies
A6068: s6067 | B6068: TV Show | C6068: =TRIM('4th netflix_titles'!$C6068) -> A Young Doctor's Notebook and Other Stories | D6068: =TRIM(C6068) -> UNKNOWN | E6068: =TRIM(D6068) -> Daniel Radcliffe, Jon Hamm, Adam Godley, Christopher Godwin, Rosie Cavaliero, Vicki Pepperdine, Margaret Clunie, Tim Steed, Shaun Pye | F6068: =TRIM(E6068) -> United Kingdom | H6068: 2013 | I6068: TV-MA | J6068: 2 Seasons | K6068: =LEFT(J6068,FIND(" ",J6068)-1) -> 2 | L6068: =RIGHT(J6068,LEN(J6068)-FIND(" ",J6068)) -> Seasons | M6068: British TV Shows, TV Comedies, TV Dramas | N6068: =TRIM(M6068) -> British TV Shows, TV Comedies, TV Dramas
A6069: s6068 | B6069: TV Show | C6069: =TRIM('4th netflix_titles'!$C6069) -> A.D. Kingdom and Empire | D6069: =TRIM(C6069) -> UNKNOWN | E6069: =TRIM(D6069) -> Juan Pablo Di Pace, Adam Levy, Chipo Chung, Babou Ceesay, Emmett Scanlan, Will Thorp, Richard Coyle, Vincent Regan, Greta Scacchi, James Callis, Joanne Whalley, Jodhi May, Chris Brazier, Fraser Ayres, JÃ³hannes Haukur JÃ³hannesson, Ken Bones, Kenneth Collard | F6069: =TRIM(E6069) -> United States | G6069: December 15, 2017 | H6069: 2015 | I6069: TV-14 | J6069: 1 Season | K6069: =LEFT(J6069,FIND(" ",J6069)-1) -> 1 | L6069: =RIGHT(J6069,LEN(J6069)-FIND(" ",J6069)) -> Season | M6069: TV Dramas | N6069: =TRIM(M6069) -> TV Dramas
A6070: s6069 | B6070: Movie | C6070: =TRIM('4th netflix_titles'!$C6070) -> A.M.I. | D6070: =TRIM(C6070) -> Rusty Nixon | E6070: =TRIM(D6070) -> Debs Howard, Philip Granger, Sam Robert Muik, Havana Guppy, Bonnie Hay, Veronica Hampson, Lori Triolo, Andrew Coghlan, Laura Mitchell, Elinet Louicius | F6070: =TRIM(E6070) -> Canada | G6070: October 1, 2020 | H6070: 2019 | I6070: TV-MA | J6070: 77 min | K6070: =LEFT(J6070,FIND(" ",J6070)-1) -> 77 | L6070: =RIGHT(J6070,LEN(J6070)-FIND(" ",J6070)) -> min | M6070: Horror Movies | N6070: =TRIM(M6070) -> Horror Movies
A6071: s6070 | B6071: Movie | C6071: =TRIM('4th netflix_titles'!$C6071) -> A.X.L. | D6071: =TRIM(C6071) -> Oliver Daly | E6071: =TRIM(D6071) -> Alex Neustaedter, Becky G., Alex MacNicoll, Dominic Rains, Thomas Jane, Lou Taylor Pucci, Patricia De Leon, Niko Guardado, Ted McGinley, Marie-FranÃ§oise Theodore, Eric Etebari, Dorian Kingi | F6071: =TRIM(E6071) -> United States | G6071: March 20, 2019 | H6071: 2018 | I6071: PG | J6071: 99 min | K6071: =LEFT(J6071,FIND(" ",J6071)-1) -> 99 | L6071: =RIGHT(J6071,LEN(J6071)-FIND(" ",J6071)) -> min | M6071: Action & Adventure, Children & Family Movies, Independent Movies | N6071: =TRIM(M6071) -> Action & Adventure, Children & Family Movies, Independent Movies
A6072: s6071 | B6072: Movie | C6072: =TRIM('4th netflix_titles'!$C6072) -> AÅŸk TesadÃ¼fleri Sever | D6072: =TRIM(C6072) -> Ã–mer Faruk Sorak | E6072: =TRIM(D6072) -> Mehmet GÃ¼nsÃ¼r, BelÃ§im Bilgin, Ayda Aksel, Altan Erkekli, Sebnem SÃ¶nmez, HÃ¼seyin Avni Danyal, Berna Konur, Ãœmit BÃ¼lent DinÃ§er | F6072: =TRIM(E6072) -> Turkey | G6072: April 4, 2018 | H6072: 2011 | I6072: TV-MA | J6072: 122 min | K6072: =LEFT(J6072,FIND(" ",J6072)-1) -> 122 | L6072: =RIGHT(J6072,LEN(J6072)-FIND(" ",J6072)) -> min | M6072: Dramas, International Movies, Romantic Movies | N6072: =TRIM(M6072) -> Dramas, International Movies, Romantic Movies
A6073: s6072 | B6073: Movie | C6073: =TRIM('4th netflix_titles'!$C6073) -> Aadu 2 | D6073: =TRIM(C6073) -> Midhun Manuel Thomas | E6073: =TRIM(D6073) -> Jayasurya, Vinayakan, Sunny Wayne, Vijay Babu, Saiju Kurup, Vineeth Mohan, Unni Rajan P. Dev, Dharmajan Bolgatty, Indrans | F6073: =TRIM(E6073) -> India | G6073: May 15, 2018 | H6073: 2017 | I6073: TV-MA | J6073: 150 min | K6073: =LEFT(J6073,FIND(" ",J6073)-1) -> 150 | L6073: =RIGHT(J6073,LEN(J6073)-FIND(" ",J6073)) -> min | M6073: Comedies, International Movies | N6073: =TRIM(M6073) -> Comedies, International Movies
A6074: s6073 | B6074: Movie | C6074: =TRIM('4th netflix_titles'!$C6074) -> Aajcha Divas Majha | D6074: =TRIM(C6074) -> Chandrakant Kulkarni | E6074: =TRIM(D6074) -> Sachin Khedekar, Ashwini Bhave, Mahesh Manjrekar, Hrishikesh Joshi, Satish Alekar, Sunil Tawde, Pushkar Shrotri, Anand Ingle | F6074: =TRIM(E6074) -> India | G6074: January 1, 2018 | H6074: 2013 | I6074: TV-PG | J6074: 126 min | K6074: =LEFT(J6074,FIND(" ",J6074)-1) -> 126 | L6074: =RIGHT(J6074,LEN(J6074)-FIND(" ",J6074)) -> min | M6074: Comedies, Dramas, International Movies | N6074: =TRIM(M6074) -> Comedies, Dramas, International Movies
A6075: s6074 | B6075: Movie | C6075: =TRIM('4th netflix_titles'!$C6075) -> Aarakshan | D6075: =TRIM(C6075) -> Prakash Jha | E6075: =TRIM(D6075) -> Amitabh Bachchan, Saif Ali Khan, Manoj Bajpayee, Deepika Padukone, Prateik, Tanvi Azmi, Saurabh Shukla, Darshan Jariwala, Yashpal Sharma, Mukesh Tiwari | F6075: =TRIM(E6075) -> India | G6075: December 31, 2019 | H6075: 2011 | I6075: TV-14 | J6075: 164 min | K6075: =LEFT(J6075,FIND(" ",J6075)-1) -> 164 | L6075: =RIGHT(J6075,LEN(J6075)-FIND(" ",J6075)) -> min | M6075: Dramas, International Movies | N6075: =TRIM(M6075) -> Dramas, International Movies
A6076: s6075 | B6076: Movie | C6076: =TRIM('4th netflix_titles'!$C6076) -> Aashayein | D6076: =TRIM(C6076) -> Nagesh Kukunoor | E6076: =TRIM(D6076) -> John Abraham, Sonal Sehgal, Prateeksha Lonkar, Girish Karnad, Farida Jalal, Ashwin Chitale, Anaitha Nair, Vikram Inamdar, Vipin Bhali, Poonam Chitale, Nagesh Kukunoor | F6076: =TRIM(E6076) -> India | G6076: October 22, 2017 | H6076: 2010 | I6076: TV-14 | J6076: 115 min | K6076: =LEFT(J6076,FIND(" ",J6076)-1) -> 115 | L6076: =RIGHT(J6076,LEN(J6076)-FIND(" ",J6076)) -> min | M6076: Dramas, International Movies | N6076: =TRIM(M6076) -> Dramas, International Movies
A6077: s6076 | B6077: Movie | C6077: =TRIM('4th netflix_titles'!$C6077) -> Aata Pita | D6077: =TRIM(C6077) -> Uttung Shelar | E6077: =TRIM(D6077) -> Sanjay Narvekar, Bharat Jadhav, Satish Phulekar, Ashwini Apte | F6077: =TRIM(E6077) -> India | G6077: January 1, 2018 | H6077: 2010 | I6077: TV-14 | J6077: 133 min | K6077: =LEFT(J6077,FIND(" ",J6077)-1) -> 133 | L6077: =RIGHT(J6077,LEN(J6077)-FIND(" ",J6077)) -> min | M6077: Comedies, Dramas, International Movies | N6077: =TRIM(M6077) -> Comedies, Dramas, International Movies
A6078: s6077 | B6078: Movie | C6078: =TRIM('4th netflix_titles'!$C6078) -> Abby Sen | D6078: =TRIM(C6078) -> Atanu Ghosh | E6078: =TRIM(D6078) -> Abir Chatterjee, Raima Sen, Arunima Ghosh, Priyanka Sarkar, Sujan Mukherjee, Kanchan Mullick, Biswanath Basu, Bhaswar Chatterjee, Swagata Basu, Tuhin Mitra, Paran Banerjee, Kharaj Mukherjee, Chiranjit | F6078: =TRIM(E6078) -> India | G6078: May 1, 2017 | H6078: 2015 | I6078: TV-PG | J6078: 127 min | K6078: =LEFT(J6078,FIND(" ",J6078)-1) -> 127 | L6078: =RIGHT(J6078,LEN(J6078)-FIND(" ",J6078)) -> min | M6078: Comedies, Dramas, International Movies | N6078: =TRIM(M6078) -> Comedies, Dramas, International Movies
A6079: s6078 | B6079: Movie | C6079: =TRIM('4th netflix_titles'!$C6079) -> Abdo Mota | D6079: =TRIM(C6079) -> UNKNOWN | E6079: =TRIM(D6079) -> Mohamed Ramadan | F6079: =TRIM(E6079) -> Egypt | G6079: April 19, 2019 | H6079: 2012 | I6079: TV-MA | J6079: 100 min | K6079: =LEFT(J6079,FIND(" ",J6079)-1) -> 100 | L6079: =RIGHT(J6079,LEN(J6079)-FIND(" ",J6079)) -> min | M6079: Action & Adventure, Dramas, International Movies | N6079: =TRIM(M6079) -> Action & Adventure, Dramas, International Movies
A6080: s6079 | B6080: Movie | C6080: =TRIM('4th netflix_titles'!$C6080) -> Abhinetri | D6080: =TRIM(C6080) -> A. L. Vijay | E6080: =TRIM(D6080) -> Tamannaah Bhatia, Prabhu Deva, Sonu Sood, Sapthagiri, Murli Sharma, R.V. Udhaykumar, Joy Mathew, Hema | F6080: =TRIM(E6080) -> India | G6080: May 1, 2018 | H6080: 2016 | I6080: TV-14 | J6080: 131 min | K6080: =LEFT(J6080,FIND(" ",J6080)-1) -> 131 | L6080: =RIGHT(J6080,LEN(J6080)-FIND(" ",J6080)) -> min | M6080: Comedies, International Movies, Sci-Fi & Fantasy | N6080: =TRIM(M6080) -> Comedies, International Movies, Sci-Fi & Fantasy
... A6175: s6174 | B6175: Movie | C6175: =TRIM('4th netflix_titles'!$C6175) -> Antariksha Ke Rakhwale | D6175: =TRIM(C6175) -> Anirban Majumder | E6175: =TRIM(D6175) -> Sonal Kaushal, Rupa Bhimani, Julie Tejwani, Sabina Malik, Jigna Bharadhwaj, Rajesh Kawa | F6175: =TRIM(E6175) -> UNKNOWN | G6175: June 18, 2019 | H6175: 2018 | I6175: TV-Y7 | J6175: 65 min | K6175: =LEFT(J6175,FIND(" ",J6175)-1) -> 65 | L6175: =RIGHT(J6175,LEN(J6175)-FIND(" ",J6175)) -> min | M6175: Children & Family Movies | N6175: =TRIM(M6175) -> Children & Family Movies
A6176: s6175 | B6176: TV Show | C6176: =TRIM('4th netflix_titles'!$C6176) -> Anthony Bourdain: Parts Unknown | D6176: =TRIM(C6176) -> UNKNOWN | E6176: =TRIM(D6176) -> Anthony Bourdain | F6176: =TRIM(E6176) -> United States | H6176: 2018 | I6176: TV-PG | J6176: 5 Seasons | K6176: =LEFT(J6176,FIND(" ",J6176)-1) -> 5 | L6176: =RIGHT(J6176,LEN(J6176)-FIND(" ",J6176)) -> Seasons | M6176: Docuseries | N6176: =TRIM(M6176) -> Docuseries
A6177: s6176 | B6177: Movie | C6177: =TRIM('4th netflix_titles'!$C6177) -> Antidote | D6177: =TRIM(C6177) -> Ken Barbet | E6177: =TRIM(D6177) -> Randy Couture, Chuck Zito, Wil Traval, Celeste Thornton, Rafael De La Fuente, Alyona Chekhova, Natali Yura, Thom Rivera | F6177: =TRIM(E6177) -> United States | G6177: April 14, 2019 | H6177: 2018 | I6177: TV-MA | J6177: 90 min | K6177: =LEFT(J6177,FIND(" ",J6177)-1) -> 90 | L6177: =RIGHT(J6177,LEN(J6177)-FIND(" ",J6177)) -> min | M6177: Action & Adventure, Horror Movies | N6177: =TRIM(M6177) -> Action & Adventure, Horror Movies
A6178: s6177 | B6178: Movie | C6178: =TRIM('4th netflix_titles'!$C6178) -> Anwar | D6178: =TRIM(C6178) -> Manish Jha | E6178: =TRIM(D6178) -> Siddharth Koirala, Nauheed Cyrusi, Manisha Koirala, Rajpal Yadav, Yashpal Sharma, Vijay Raaz, Hiten Tejwani, Sudhir Pandey, Sanjay Mishra, Lalit Tiwari | F6178: =TRIM(E6178) -> India | G6178: December 31, 2019 | H6178: 2007 | I6178: TV-14 | J6178: 134 min | K6178: =LEFT(J6178,FIND(" ",J6178)-1) -> 134 | L6178: =RIGHT(J6178,LEN(J6178)-FIND(" ",J6178)) -> min | M6178: Dramas, Independent Movies, International Movies | N6178: =TRIM(M6178) -> Dramas, Independent Movies, International Movies
A6179: s6178 | B6179: TV Show | C6179: =TRIM('4th netflix_titles'!$C6179) -> å¿è€…ãƒãƒƒãƒˆãƒªãã‚“ | D6179: =TRIM(C6179) -> UNKNOWN | E6179: =TRIM(D6179) -> Not Available | F6179: =TRIM(E6179) -> Japan | G6179: December 23, 2018 | H6179: 2012 | I6179: TV-Y7 | J6179: 2 Seasons | K6179: =LEFT(J6179,FIND(" ",J6179)-1) -> 2 | L6179: =RIGHT(J6179,LEN(J6179)-FIND(" ",J6179)) -> Seasons | M6179: Anime Series, Kids' TV | N6179: =TRIM(M6179) -> Anime Series, Kids' TV
A6180: s6179 | B6180: Movie | C6180: =TRIM('4th netflix_titles'!$C6180) -> Apache Warrior | D6180: =TRIM(C6180) -> David Salzberg, Christian Tureaud | E6180: =TRIM(D6180) -> Not Available | F6180: =TRIM(E6180) -> United States | G6180: November 1, 2019 | H6180: 2017 | I6180: TV-MA | J6180: 89 min | K6180: =LEFT(J6180,FIND(" ",J6180)-1) -> 89 | L6180: =RIGHT(J6180,LEN(J6180)-FIND(" ",J6180)) -> min | M6180: Documentaries | N6180: =TRIM(M6180) -> Documentaries
A6181: s6180 | B6181: Movie | C6181: =TRIM('4th netflix_titles'!$C6181) -> APEX: The Story of the Hypercar | D6181: =TRIM(C6181) -> J.F. Musial, Josh Vietze | E6181: =TRIM(D6181) -> Zachary Levi | F6181: =TRIM(E6181) -> United States | G6181: August 1, 2016 | H6181: 2016 | I6181: NR | J6181: 86 min | K6181: =LEFT(J6181,FIND(" ",J6181)-1) -> 86 | L6181: =RIGHT(J6181,LEN(J6181)-FIND(" ",J6181)) -> min | M6181: Documentaries | N6181: =TRIM(M6181) -> Documentaries
A6182: s6181 | B6182: Movie | C6182: =TRIM('4th netflix_titles'!$C6182) -> Apollo 18 | D6182: =TRIM(C6182) -> Gonzalo LÃ³pez-Gallego | E6182: =TRIM(D6182) -> Warren Christie, Lloyd Owen, Ryan Robbins, Michael Kopsa, Andrew Airlie | F6182: =TRIM(E6182) -> United States, Canada | G6182: March 9, 2019 | H6182: 2011 | I6182: PG-13 | J6182: 87 min | K6182: =LEFT(J6182,FIND(" ",J6182)-1) -> 87 | L6182: =RIGHT(J6182,LEN(J6182)-FIND(" ",J6182)) -> min | M6182: Horror Movies, Sci-Fi & Fantasy, Thrillers | N6182: =TRIM(M6182) -> Horror Movies, Sci-Fi & Fantasy, Thrillers
A6183: s6182 | B6183: Movie | C6183: =TRIM('4th netflix_titles'!$C6183) -> April and the Extraordinary World | D6183: =TRIM(C6183) -> Christian Desmares, Franck Ekinci | E6183: =TRIM(D6183) -> Angela Galuppo, Paul Giamatti, Susan Sarandon, Tony Hale, J.K. Simmons, Tony Robinow, Mark Camacho, Tod Fennell, Carlos Alazraqui, Kari Wahlgren | F6183: =TRIM(E6183) -> France, Canada, Belgium | G6183: October 1, 2017 | H6183: 2015 | I6183: PG | J6183: 107 min | K6183: =LEFT(J6183,FIND(" ",J6183)-1) -> 107 | L6183: =RIGHT(J6183,LEN(J6183)-FIND(" ",J6183)) -> min | M6183: Action & Adventure, Comedies, International Movies | N6183: =TRIM(M6183) -> Action & Adventure, Comedies, International Movies
A6184: s6183 | B6184: Movie | C6184: =TRIM('4th netflix_titles'!$C6184) -> Aram, Aram | D6184: =TRIM(C6184) -> Christopher Chambers | E6184: =TRIM(D6184) -> John Roohinian, Levon Sharafyan, Sevak Hakoyan, David Villada, Mike Ghader, Razmik Mansuryan, Lorita Meg, Amy Sanders, Alla Tumanian | F6184: =TRIM(E6184) -> United States | G6184: February 15, 2017 | H6184: 2015 | I6184: TV-14 | J6184: 79 min | K6184: =LEFT(J6184,FIND(" ",J6184)-1) -> 79 | L6184: =RIGHT(J6184,LEN(J6184)-FIND(" ",J6184)) -> min | M6184: Dramas, Independent Movies | N6184: =TRIM(M6184) -> Dramas, Independent Movies
A6185: s6184 | B6185: Movie | C6185: =TRIM('4th netflix_titles'!$C6185) -> Are We Done Yet? | D6185: =TRIM(C6185) -> Khaled El Halafawy | E6185: =TRIM(D6185) -> Ahmed Eid, Ayten Amer, Ahmed Fouad Selim, Mohsen Mansour | F6185: =TRIM(E6185) -> Egypt | G6185: August 1, 2019 | H6185: 2018 | I6185: TV-14 | J6185: 87 min | K6185: =LEFT(J6185,FIND(" ",J6185)-1) -> 87 | L6185: =RIGHT(J6185,LEN(J6185)-FIND(" ",J6185)) -> min | M6185: Comedies, Dramas, International Movies | N6185: =TRIM(M6185) -> Comedies, Dramas, International Movies
A6186: s6185 | B6186: Movie | C6186: =TRIM('4th netflix_titles'!$C6186) -> Arisan 2 | D6186: =TRIM(C6186) -> Nia Dinata | E6186: =TRIM(D6186) -> Surya Saputra, Cut Mini Theo, Tora Sudiro | F6186: =TRIM(E6186) -> Indonesia | G6186: September 15, 2018 | H6186: 2011 | I6186: TV-14 | J6186: 113 min | K6186: =LEFT(J6186,FIND(" ",J6186)-1) -> 113 | L6186: =RIGHT(J6186,LEN(J6186)-FIND(" ",J6186)) -> min | M6186: Comedies, Dramas, International Movies | N6186: =TRIM(M6186) -> Comedies, Dramas, International Movies
A6187: s6186 | B6187: Movie | C6187: =TRIM('4th netflix_titles'!$C6187) -> Arthur | D6187: =TRIM(C6187) -> Jason Winer | E6187: =TRIM(D6187) -> Russell Brand, Helen Mirren, Greta Gerwig, Jennifer Garner, Geraldine James, Luis GuzmÃ¡n, Nick Nolte, Christina Jacquelyn Calph, Murphy Guyer, JosÃ© RamÃ³n Rosario | F6187: =TRIM(E6187) -> United States | G6187: April 1, 2019 | H6187: 2011 | I6187: PG-13 | J6187: 110 min | K6187: =LEFT(J6187,FIND(" ",J6187)-1) -> 110 | L6187: =RIGHT(J6187,LEN(J6187)-FIND(" ",J6187)) -> min | M6187: Comedies, Romantic Movies | N6187: =TRIM(M6187) -> Comedies, Romantic Movies
A6188: s6187 | B6188: Movie | C6188: =TRIM('4th netflix_titles'!$C6188) -> Arthur Christmas | D6188: =TRIM(C6188) -> Sarah Smith | E6188: =TRIM(D6188) -> James McAvoy, Hugh Laurie, Bill Nighy, Jim Broadbent, Imelda Staunton, Ashley Jensen, Ramona Marquez, Marc Wootton, Laura Linney, Eva Longoria, Michael Palin, Joan Cusack, Deborah Findlay, Rich Fulcher, Sarah Smith, Clint Dyer, Kerry Shale, Stewart Lee, Bronagh Gallagher, Kevin Cecil, Alistair McGowan, David Menkin, Kris Pearn, Ian Ashpitel, Rich Hall, Seeta Indrani, Jane Horrocks, Peter Baynham, Emma Kennedy, Dominic West, Jerry Lambert, Julia Davis, Robbie Coltrane, Iain McKee, Sanjeev Bhaskar, Andy Serkis, Tamsin Greig, Rhys Darby, Seamus Malone, Cody Cameron, David Schneider, Kevin Eldon, Danny John-Jules, Brian Cummings | F6188: =TRIM(E6188) -> United Kingdom, United States | G6188: January 1, 2020 | H6188: 2011 | I6188: PG | J6188: 98 min | K6188: =LEFT(J6188,FIND(" ",J6188)-1) -> 98 | L6188: =RIGHT(J6188,LEN(J6188)-FIND(" ",J6188)) -> min | M6188: Children & Family Movies, Comedies | N6188: =TRIM(M6188) -> Children & Family Movies, Comedies
... A6796: s6795 | B6796: Movie | C6796: =TRIM('4th netflix_titles'!$C6796) -> Frances Ha | D6796: =TRIM(C6796) -> Noah Baumbach | E6796: =TRIM(D6796) -> Greta Gerwig, Mickey Sumner, Charlotte d'Amboise, Adam Driver, Hannah Dunne, Michael Esper, Grace Gummer, Patrick Heusinger, Josh Hamilton, Cindy Katz, Maya Kazan, Justine Lupe, Britta Phillips, Juliet Rylance, Dean Wareham, Michael Zegen | F6796: =TRIM(E6796) -> United States, Brazil | G6796: October 1, 2017 | H6796: 2012 | I6796: R | J6796: 86 min | K6796: =LEFT(J6796,FIND(" ",J6796)-1) -> 86 | L6796: =RIGHT(J6796,LEN(J6796)-FIND(" ",J6796)) -> min | M6796: Comedies, Dramas, Independent Movies | N6796: =TRIM(M6796) -> Comedies, Dramas, Independent Movies
A6797: s6796 | B6797: TV Show | C6797: =TRIM('4th netflix_titles'!$C6797) -> Frasier | D6797: =TRIM(C6797) -> UNKNOWN | E6797: =TRIM(D6797) -> Kelsey Grammer, Jane Leeves, David Hyde Pierce, Peri Gilpin, John Mahoney, Dan Butler | F6797: =TRIM(E6797) -> United States | H6797: 2003 | I6797: TV-PG | J6797: 11 Seasons | K6797: =LEFT(J6797,FIND(" ",J6797)-1) -> 11 | L6797: =RIGHT(J6797,LEN(J6797)-FIND(" ",J6797)) -> Seasons | M6797: Classic & Cult TV, TV Comedies | N6797: =TRIM(M6797) -> Classic & Cult TV, TV Comedies
A6798: s6797 | B6798: Movie | C6798: =TRIM('4th netflix_titles'!$C6798) -> Freak Show | D6798: =TRIM(C6798) -> Trudie Styler | E6798: =TRIM(D6798) -> Alex Lawther, Abigail Breslin, AnnaSophia Robb, Ian Nelson, Celia Weston, Laverne Cox, Bette Midler, Willa Fitzgerald, Larry Pine, John McEnroe, Mickey Sumner, Daniel Bellomy, Wally Dunn, Marceline Hugot | F6798: =TRIM(E6798) -> United States | G6798: August 13, 2020 | H6798: 2018 | I6798: TV-MA | J6798: 91 min | K6798: =LEFT(J6798,FIND(" ",J6798)-1) -> 91 | L6798: =RIGHT(J6798,LEN(J6798)-FIND(" ",J6798)) -> min | M6798: Comedies, Dramas, Independent Movies | N6798: =TRIM(M6798) -> Comedies, Dramas, Independent Movies
A6799: s6798 | B6799: Movie | C6799: =TRIM('4th netflix_titles'!$C6799) -> Fred Claus | D6799: =TRIM(C6799) -> David Dobkin | E6799: =TRIM(D6799) -> Vince Vaughn, Paul Giamatti, John Michael Higgins, Miranda Richardson, Rachel Weisz, Kathy Bates, Trevor Peacock, Ludacris, Elizabeth Banks | F6799: =TRIM(E6799) -> United States | G6799: January 1, 2021 | H6799: 2007 | I6799: PG | J6799: 115 min | K6799: =LEFT(J6799,FIND(" ",J6799)-1) -> 115 | L6799: =RIGHT(J6799,LEN(J6799)-FIND(" ",J6799)) -> min | M6799: Children & Family Movies, Comedies | N6799: =TRIM(M6799) -> Children & Family Movies, Comedies
A6800: s6799 | B6800: Movie | C6800: =TRIM('4th netflix_titles'!$C6800) -> Free Willy | D6800: =TRIM(C6800) -> Simon Wincer | E6800: =TRIM(D6800) -> Jason James Richter, Lori Petty, Jayne Atkinson, August Schellenberg, Michael Madsen, Michael Ironside, Richard Riehle, Mykelti Williamson, Michael Bacall, Danielle Harris | F6800: =TRIM(E6800) -> United States, France, Mexico | G6800: January 1, 2020 | H6800: 1993 | I6800: PG | J6800: 112 min | K6800: =LEFT(J6800,FIND(" ",J6800)-1) -> 112 | L6800: =RIGHT(J6800,LEN(J6800)-FIND(" ",J6800)) -> min | M6800: Children & Family Movies, Dramas | N6800: =TRIM(M6800) -> Children & Family Movies, Dramas
A6801: s6800 | B6801: Movie | C6801: =TRIM('4th netflix_titles'!$C6801) -> Freeway: Crack in the System | D6801: =TRIM(C6801) -> Marc Levin | E6801: =TRIM(D6801) -> Freeway Rick Ross | F6801: =TRIM(E6801) -> United States, Nicaragua | G6801: December 15, 2017 | H6801: 2015 | I6801: R | J6801: 103 min | K6801: =LEFT(J6801,FIND(" ",J6801)-1) -> 103 | L6801: =RIGHT(J6801,LEN(J6801)-FIND(" ",J6801)) -> min | M6801: Documentaries | N6801: =TRIM(M6801) -> Documentaries
A6802: s6801 | B6802: Movie | C6802: =TRIM('4th netflix_titles'!$C6802) -> Freezer's Campaign | D6802: =TRIM(C6802) -> Sameh Abdulaziz | E6802: =TRIM(D6802) -> Bayyumi Fuad, Chico, Hesham Maged, Ahmed Fathy, Nesreen Ameen, Dareen Haddad, Bushra, Samy Maghawry | F6802: =TRIM(E6802) -> Egypt | G6802: June 6, 2019 | H6802: 2016 | I6802: TV-MA | J6802: 116 min | K6802: =LEFT(J6802,FIND(" ",J6802)-1) -> 116 | L6802: =RIGHT(J6802,LEN(J6802)-FIND(" ",J6802)) -> min | M6802: Comedies, International Movies | N6802: =TRIM(M6802) -> Comedies, International Movies
A6803: s6802 | B6803: Movie | C6803: =TRIM('4th netflix_titles'!$C6803) -> French Dirty | D6803: =TRIM(C6803) -> Wade Allain-Marcus, Jesse Allain-Marcus | E6803: =TRIM(D6803) -> Wade Allain-Marcus, Arjun Gupta, Melina Lizette, Elsa Biedermann, Katie Blake, Santana Dempsey | F6803: =TRIM(E6803) -> United States | G6803: February 4, 2016 | H6803: 2015 | I6803: TV-MA | J6803: 72 min | K6803: =LEFT(J6803,FIND(" ",J6803)-1) -> 72 | L6803: =RIGHT(J6803,LEN(J6803)-FIND(" ",J6803)) -> min | M6803: Dramas, Independent Movies | N6803: =TRIM(M6803) -> Dramas, Independent Movies
A6804: s6803 | B6804: Movie | C6804: =TRIM('4th netflix_titles'!$C6804) -> Freshman Year | D6804: =TRIM(C6804) -> Jude Okwudiafor Johnson | E6804: =TRIM(D6804) -> Diallo Thompson, Natalia Dominguez, Benjamin A. Onyango, Gregory Alan Williams, Desalene Jones, Wynton Odd, Ed Gonzalez Moreno, Natasha Dee Davis, Cameron Schaefer, Joshua Flores-Q | F6804: =TRIM(E6804) -> United States | G6804: March 3, 2020 | H6804: 2019 | I6804: TV-PG | J6804: 104 min | K6804: =LEFT(J6804,FIND(" ",J6804)-1) -> 104 | L6804: =RIGHT(J6804,LEN(J6804)-FIND(" ",J6804)) -> min | M6804: Dramas, Faith & Spirituality | N6804: =TRIM(M6804) -> Dramas, Faith & Spirituality
A6805: s6804 | B6805: TV Show | C6805: =TRIM('4th netflix_titles'!$C6805) -> Friday Night Tykes | D6805: =TRIM(C6805) -> UNKNOWN | E6805: =TRIM(D6805) -> Not Available | F6805: =TRIM(E6805) -> United States | G6805: January 17, 2018 | H6805: 2017 | I6805: TV-PG | J6805: 4 Seasons | K6805: =LEFT(J6805,FIND(" ",J6805)-1) -> 4 | L6805: =RIGHT(J6805,LEN(J6805)-FIND(" ",J6805)) -> Seasons | M6805: Docuseries, Reality TV | N6805: =TRIM(M6805) -> Docuseries, Reality TV
A6806: s6805 | B6806: Movie | C6806: =TRIM('4th netflix_titles'!$C6806) -> Friday the 13th | D6806: =TRIM(C6806) -> Marcus Nispel | E6806: =TRIM(D6806) -> Jared Padalecki, Danielle Panabaker, Amanda Righetti, Travis Van Winkle, Aaron Yoo, Derek Mears, Jonathan Sadowski, Julianna Guill, Ben Feldman, Arlen Escarpeta, Ryan Hansen | F6806: =TRIM(E6806) -> United States | G6806: January 1, 2020 | H6806: 2009 | I6806: R | J6806: 97 min | K6806: =LEFT(J6806,FIND(" ",J6806)-1) -> 97 | L6806: =RIGHT(J6806,LEN(J6806)-FIND(" ",J6806)) -> min | M6806: Horror Movies | N6806: =TRIM(M6806) -> Horror Movies
A6807: s6806 | B6807: Movie | C6807: =TRIM('4th netflix_titles'!$C6807) -> Friend Request | D6807: =TRIM(C6807) -> Simon Verhoeven | E6807: =TRIM(D6807) -> Alycia Debnam-Carey, William Moseley, Connor Paolo, Brit Morgan, Brooke Markham, Sean Marquette, Liesl Ahlers, Shashawnee Hall, Susan Danford | F6807: =TRIM(E6807) -> Germany | G6807: April 18, 2018 | H6807: 2016 | I6807: R | J6807: 92 min | K6807: =LEFT(J6807,FIND(" ",J6807)-1) -> 92 | L6807: =RIGHT(J6807,LEN(J6807)-FIND(" ",J6807)) -> min | M6807: Horror Movies, International Movies | N6807: =TRIM(M6807) -> Horror Movies, International Movies
A6808: s6807 | B6808: TV Show | C6808: =TRIM('4th netflix_titles'!$C6808) -> Friends | D6808: =TRIM(C6808) -> UNKNOWN | E6808: =TRIM(D6808) -> Jennifer Aniston, Courteney Cox, Lisa Kudrow, Matt LeBlanc, Matthew Perry, David Schwimmer | F6808: =TRIM(E6808) -> United States | H6808: 2003 | I6808: TV-14 | J6808: 10 Seasons | K6808: =LEFT(J6808,FIND(" ",J6808)-1) -> 10 | L6808: =RIGHT(J6808,LEN(J6808)-FIND(" ",J6808)) -> Seasons | M6808: Classic & Cult TV, TV Comedies | N6808: =TRIM(M6808) -> Classic & Cult TV, TV Comedies
A6809: s6808 | B6809: Movie | C6809: =TRIM('4th netflix_titles'!$C6809) -> From Japan to Egypt | D6809: =TRIM(C6809) -> Mahmoud Karim | E6809: =TRIM(D6809) -> Ahmed Eid, Saki Tsukamoto, Nada Moussa, Mohammed Tharwat | F6809: =TRIM(E6809) -> Egypt | G6809: June 6, 2019 | H6809: 2017 | I6809: TV-14 | J6809: 93 min | K6809: =LEFT(J6809,FIND(" ",J6809)-1) -> 93 | L6809: =RIGHT(J6809,LEN(J6809)-FIND(" ",J6809)) -> min | M6809: Children & Family Movies, Comedies, Dramas | N6809: =TRIM(M6809) -> Children & Family Movies, Comedies, Dramas
A6810: s6809 | B6810: Movie | C6810: =TRIM('4th netflix_titles'!$C6810) -> From Paris with Love | D6810: =TRIM(C6810) -> Pierre Morel | E6810: =TRIM(D6810) -> John Travolta, Jonathan Rhys Meyers, Kasia Smutniak, Richard Durden, Bing Yin, Amber Rose Revah, Eric Godon, FranÃ§ois Bredon, Chems Dahmani, Sami Darr, Didier Constant | F6810: =TRIM(E6810) -> France, United Kingdom, United States | G6810: September 8, 2020 | H6810: 2010 | I6810: R | J6810: 93 min | K6810: =LEFT(J6810,FIND(" ",J6810)-1) -> 93 | L6810: =RIGHT(J6810,LEN(J6810)-FIND(" ",J6810)) -> min | M6810: Action & Adventure, International Movies | N6810: =TRIM(M6810) -> Action & Adventure, International Movies
A6811: s6810 | B6811: Movie | C6811: =TRIM('4th netflix_titles'!$C6811) -> Froning: The Fittest Man in History | D6811: =TRIM(C6811) -> Heber Cannon | E6811: =TRIM(D6811) -> Rich Froning | F6811: =TRIM(E6811) -> United States | G6811: July 15, 2018 | H6811: 2016 | I6811: PG | J6811: 99 min | K6811: =LEFT(J6811,FIND(" ",J6811)-1) -> 99 | L6811: =RIGHT(J6811,LEN(J6811)-FIND(" ",J6811)) -> min | M6811: Documentaries, International Movies, Sports Movies | N6811: =TRIM(M6811) -> Documentaries, International Movies, Sports Movies
A6812: s6811 | B6812: TV Show | C6812: =TRIM('4th netflix_titles'!$C6812) -> Frozen Planet | D6812: =TRIM(C6812) -> Alastair Fothergill | E6812: =TRIM(D6812) -> David Attenborough | F6812: =TRIM(E6812) -> United Kingdom, United States, Spain, Germany, Greece, Canada | G6812: January 28, 2016 | H6812: 2011 | I6812: TV-PG | J6812: 1 Season | K6812: =LEFT(J6812,FIND(" ",J6812)-1) -> 1 | L6812: =RIGHT(J6812,LEN(J6812)-FIND(" ",J6812)) -> Season | M6812: British TV Shows, Docuseries, International TV Shows | N6812: =TRIM(M6812) -> British TV Shows, Docuseries, International TV Shows
A6813: s6812 | B6813: Movie | C6813: =TRIM('4th netflix_titles'!$C6813) -> Frozen Planet: On Thin Ice | D6813: =TRIM(C6813) -> UNKNOWN | E6813: =TRIM(D6813) -> David Attenborough | F6813: =TRIM(E6813) -> United Kingdom, United States, Spain, Germany, Greece, Canada | G6813: January 28, 2016 | H6813: 2011 | I6813: TV-PG | J6813: 47 min | K6813: =LEFT(J6813,FIND(" ",J6813)-1) -> 47 | L6813: =RIGHT(J6813,LEN(J6813)-FIND(" ",J6813)) -> min | M6813: Movies | N6813: =TRIM(M6813) -> Movies
A6814: s6813 | B6814: Movie | C6814: =TRIM('4th netflix_titles'!$C6814) -> Frozen Planet: The Epic Journey | D6814: =TRIM(C6814) -> UNKNOWN | E6814: =TRIM(D6814) -> David Attenborough | F6814: =TRIM(E6814) -> United Kingdom, United States, Spain, Germany, Greece, Canada | G6814: January 28, 2016 | H6814: 2011 | I6814: TV-PG | J6814: 52 min | K6814: =LEFT(J6814,FIND(" ",J6814)-1) -> 52 | L6814: =RIGHT(J6814,LEN(J6814)-FIND(" ",J6814)) -> min | M6814: Movies | N6814: =TRIM(M6814) -> Movies
A6815: s6814 | B6815: Movie | C6815: =TRIM('4th netflix_titles'!$C6815) -> Frozen River | D6815: =TRIM(C6815) -> Courtney Hunt | E6815: =TRIM(D6815) -> Melissa Leo, Misty Upham, Charlie McDermott, Michael O'Keefe, Mark Boone Junior, James Reilly, Jay Klaitz, John Canoe, Dylan Carusona, Michael Sky | F6815: =TRIM(E6815) -> United States | G6815: July 1, 2019 | H6815: 2008 | I6815: R | J6815: 97 min | K6815: =LEFT(J6815,FIND(" ",J6815)-1) -> 97 | L6815: =RIGHT(J6815,LEN(J6815)-FIND(" ",J6815)) -> min | M6815: Dramas, Independent Movies | N6815: =TRIM(M6815) -> Dramas, Independent Movies
A6816: s6815 | B6816: Movie | C6816: =TRIM('4th netflix_titles'!$C6816) -> Full Out | D6816: =TRIM(C6816) -> Sean Cisterna | E6816: =TRIM(D6816) -> Jennifer Beals, Ana Golja, Art Hindle, Jake Epstein, Ramona Milano, Trevor Tordjman, Lamar Johnson, Asha Bromfield, Sarah Fisher | F6816: =TRIM(E6816) -> Canada, United States | G6816: September 1, 2016 | H6816: 2015 | I6816: TV-PG | J6816: 88 min | K6816: =LEFT(J6816,FIND(" ",J6816)-1) -> 88 | L6816: =RIGHT(J6816,LEN(J6816)-FIND(" ",J6816)) -> min | M6816: Children & Family Movies, Dramas, Sports Movies | N6816: =TRIM(M6816) -> Children & Family Movies, Dramas, Sports Movies
A6817: s6816 | B6817: Movie | C6817: =TRIM('4th netflix_titles'!$C6817) -> Functional Fitness | D6817: =TRIM(C6817) -> Bob Rose | E6817: =TRIM(D6817) -> Not Available | F6817: =TRIM(E6817) -> United States | G6817: January 1, 2018 | H6817: 2016 | I6817: TV-MA | J6817: 106 min | K6817: =LEFT(J6817,FIND(" ",J6817)-1) -> 106 | L6817: =RIGHT(J6817,LEN(J6817)-FIND(" ",J6817)) -> min | M6817: Documentaries | N6817: =TRIM(M6817) -> Documentaries
A6818: s6817 | B6818: Movie | C6818: =TRIM('4th netflix_titles'!$C6818) -> Furie | D6818: =TRIM(C6818) -> Le Van Kiet | E6818: =TRIM(D6818) -> Ngo Thanh Van, Phan Thanh Nhien, Mai Cat Vi, Thanh Hoa, Pham Anh Khoa | F6818: =TRIM(E6818) -> Vietnam | G6818: September 25, 2019 | H6818: 2019 | I6818: TV-MA | J6818: 97 min | K6818: =LEFT(J6818,FIND(" ",J6818)-1) -> 97 | L6818: =RIGHT(J6818,LEN(J6818)-FIND(" ",J6818)) -> min | M6818: Action & Adventure, Dramas, International Movies | N6818: =TRIM(M6818) -> Action & Adventure, Dramas, International Movies
A6819: s6818 | B6819: Movie | C6819: =TRIM('4th netflix_titles'!$C6819) -> Furthest Witness | D6819: =TRIM(C6819) -> Adam Del Giudice | E6819: =TRIM(D6819) -> Aaron Stanford, Teri Reeves, Sean Patrick Flanery, Forrest Fyre, Steven Michael Quezada, Paul Blott, Travis Hammer, Ryan Begay, Jermaine Washington, Vincent McDaniel | F6819: =TRIM(E6819) -> United States, United Kingdom | G6819: April 24, 2019 | H6819: 2017 | I6819: TV-MA | J6819: 88 min | K6819: =LEFT(J6819,FIND(" ",J6819)-1) -> 88 | L6819: =RIGHT(J6819,LEN(J6819)-FIND(" ",J6819)) -> min | M6819: Dramas, Thrillers | N6819: =TRIM(M6819) -> Dramas, Thrillers
A6820: s6819 | B6820: Movie | C6820: =TRIM('4th netflix_titles'!$C6820) -> G-Force | D6820: =TRIM(C6820) -> Hoyt Yeatman | E6820: =TRIM(D6820) -> Bill Nighy, Will Arnett, Zach Galifianakis, Kelli Garner, Tyler Patrick Jones, Piper Mackenzie Harris, Gabriel Casseus, Jack Conley, Niecy Nash, Justin Mentell, Nicolas Cage, Sam Rockwell, Jon Favreau, PenÃ©lope Cruz, Steve Buscemi, Tracy Morgan | F6820: =TRIM(E6820) -> United States | G6820: March 15, 2019 | H6820: 2009 | I6820: PG | J6820: 88 min | K6820: =LEFT(J6820,FIND(" ",J6820)-1) -> 88 | L6820: =RIGHT(J6820,LEN(J6820)-FIND(" ",J6820)) -> min | M6820: Children & Family Movies, Comedies | N6820: =TRIM(M6820) -> Children & Family Movies, Comedies
... A6902: s6901 | B6902: Movie | C6902: =TRIM('4th netflix_titles'!$C6902) -> Gun Runners | D6902: =TRIM(C6902) -> Anjali Nayar | E6902: =TRIM(D6902) -> Not Available | F6902: =TRIM(E6902) -> Canada | G6902: February 1, 2017 | H6902: 2015 | I6902: TV-PG | J6902: 90 min | K6902: =LEFT(J6902,FIND(" ",J6902)-1) -> 90 | L6902: =RIGHT(J6902,LEN(J6902)-FIND(" ",J6902)) -> min | M6902: Documentaries, International Movies, Sports Movies | N6902: =TRIM(M6902) -> Documentaries, International Movies, Sports Movies
A6903: s6902 | B6903: TV Show | C6903: =TRIM('4th netflix_titles'!$C6903) -> Gunslinger Girl | D6903: =TRIM(C6903) -> UNKNOWN | E6903: =TRIM(D6903) -> Yuuka Nanri, Kanako Mitsuhashi, Eri Sendai, Ami Koshimizu, Hidenobu Kiuchi, Mitsuru Miyamoto, Masashi Ebara, Norihiro Inoue, Rie Nakagawa, Masami Iwasaki, Laura Bailey, Luci Christian, Caitlin Glass, Alese Johnson, Monica Rial, Jerry Jewell, Stephanie Young, Mike McFarland | F6903: =TRIM(E6903) -> Japan | H6903: 2008 | I6903: TV-14 | J6903: 2 Seasons | K6903: =LEFT(J6903,FIND(" ",J6903)-1) -> 2 | L6903: =RIGHT(J6903,LEN(J6903)-FIND(" ",J6903)) -> Seasons | M6903: Anime Series, Crime TV Shows | N6903: =TRIM(M6903) -> Anime Series, Crime TV Shows
A6904: s6903 | B6904: Movie | C6904: =TRIM('4th netflix_titles'!$C6904) -> Guy Martin: Last Flight of the Vulcan Bomber | D6904: =TRIM(C6904) -> James Woodroffe | E6904: =TRIM(D6904) -> Guy Martin, Kevin Stone, Shaun Dooley | F6904: =TRIM(E6904) -> United Kingdom | G6904: July 26, 2019 | H6904: 2015 | I6904: TV-G | J6904: 57 min | K6904: =LEFT(J6904,FIND(" ",J6904)-1) -> 57 | L6904: =RIGHT(J6904,LEN(J6904)-FIND(" ",J6904)) -> min | M6904: Documentaries, International Movies | N6904: =TRIM(M6904) -> Documentaries, International Movies
A6905: s6904 | B6905: Movie | C6905: =TRIM('4th netflix_titles'!$C6905) -> HÃ©roes | D6905: =TRIM(C6905) -> Esteban Vidal | E6905: =TRIM(D6905) -> Fabrizio Copano, Juanita Ringeling, Fernando AlarcÃ³n, Delfina GuzmÃ¡n, Paty CofrÃ©, AndrÃ©s RillÃ³n, Julio Jung, NicolÃ¡s OyarzÃºn | F6905: =TRIM(E6905) -> Chile | G6905: August 19, 2018 | H6905: 2015 | I6905: TV-MA | J6905: 91 min | K6905: =LEFT(J6905,FIND(" ",J6905)-1) -> 91 | L6905: =RIGHT(J6905,LEN(J6905)-FIND(" ",J6905)) -> min | M6905: Comedies, International Movies | N6905: =TRIM(M6905) -> Comedies, International Movies
A6906: s6905 | B6906: Movie | C6906: =TRIM('4th netflix_titles'!$C6906) -> HÃ¼kÃ¼met Kadin | D6906: =TRIM(C6906) -> Sermiyan Midyat | E6906: =TRIM(D6906) -> Demet AkbaÄŸ, Sermiyan Midyat, Mahir Ä°pek, GÃ¼lhan Tekin, Burcu GÃ¶nder, Cezmi BaskÄ±n, Renan Bilek, Ayberk Attila, RÄ±za AkÄ±n, BÃ¼lent Ã‡olak | F6906: =TRIM(E6906) -> Turkey | G6906: March 10, 2017 | H6906: 2013 | I6906: TV-MA | J6906: 100 min | K6906: =LEFT(J6906,FIND(" ",J6906)-1) -> 100 | L6906: =RIGHT(J6906,LEN(J6906)-FIND(" ",J6906)) -> min | M6906: Comedies, International Movies | N6906: =TRIM(M6906) -> Comedies, International Movies
A6907: s6906 | B6907: Movie | C6907: =TRIM('4th netflix_titles'!$C6907) -> HÃ¼kÃ¼met Kadin 2 | D6907: =TRIM(C6907) -> Sermiyan Midyat | E6907: =TRIM(D6907) -> Demet AkbaÄŸ, Sermiyan Midyat, Mahir Ä°pek, GÃ¼lhan Tekin, Burcu GÃ¶nder, Mine Åženhuy Teber, Osman AlkaÅŸ, BÃ¼lent Ã‡olak, Olgun Toker, DoÄŸukan Polat | F6907: =TRIM(E6907) -> Turkey | G6907: March 10, 2017 | H6907: 2013 | I6907: TV-14 | J6907: 101 min | K6907: =LEFT(J6907,FIND(" ",J6907)-1) -> 101 | L6907: =RIGHT(J6907,LEN(J6907)-FIND(" ",J6907)) -> min | M6907: Comedies, International Movies | N6907: =TRIM(M6907) -> Comedies, International Movies
A6908: s6907 | B6908: TV Show | C6908: =TRIM('4th netflix_titles'!$C6908) -> Ha Unlimited | D6908: =TRIM(C6908) -> UNKNOWN | E6908: =TRIM(D6908) -> Tuck Boriboon, Ball Chernyim, Naâ€™Kom Chuanchuen | F6908: =TRIM(E6908) -> UNKNOWN | G6908: May 11, 2018 | H6908: 2016 | I6908: TV-MA | J6908: 2 Seasons | K6908: =LEFT(J6908,FIND(" ",J6908)-1) -> 2 | L6908: =RIGHT(J6908,LEN(J6908)-FIND(" ",J6908)) -> Seasons | M6908: International TV Shows, TV Comedies | N6908: =TRIM(M6908) -> International TV Shows, TV Comedies
A6909: s6908 | B6909: Movie | C6909: =TRIM('4th netflix_titles'!$C6909) -> Haapus | D6909: =TRIM(C6909) -> UNKNOWN | E6909: =TRIM(D6909) -> Makarand Anaspure, Madhura Velankar, Subodh Bhave | F6909: =TRIM(E6909) -> India | G6909: March 15, 2018 | H6909: 2010 | I6909: TV-14 | J6909: 138 min | K6909: =LEFT(J6909,FIND(" ",J6909)-1) -> 138 | L6909: =RIGHT(J6909,LEN(J6909)-FIND(" ",J6909)) -> min | M6909: Comedies, Dramas, International Movies | N6909: =TRIM(M6909) -> Comedies, Dramas, International Movies
A6910: s6909 | B6910: Movie | C6910: =TRIM('4th netflix_titles'!$C6910) -> Hadi Ä°nÅŸallah | D6910: =TRIM(C6910) -> Ali Taner BaltacÄ± | E6910: =TRIM(D6910) -> BÃ¼ÅŸra Pekin, Murat Boz, Cezmi BaskÄ±n, Åžinasi Yurtsever, Ä°dil Dizdar, HÃ¼lya GÃ¼lsen Irmak, Canan Ã–zer, Åženay Bozoklar, Emrah Kaman, MÃ¼jde Uzman | F6910: =TRIM(E6910) -> Turkey | G6910: April 4, 2018 | H6910: 2014 | I6910: TV-14 | J6910: 95 min | K6910: =LEFT(J6910,FIND(" ",J6910)-1) -> 95 | L6910: =RIGHT(J6910,LEN(J6910)-FIND(" ",J6910)) -> min | M6910: Comedies, International Movies, Romantic Movies | N6910: =TRIM(M6910) -> Comedies, International Movies, Romantic Movies
A6911: s6910 | B6911: Movie | C6911: =TRIM('4th netflix_titles'!$C6911) -> Hairspray | D6911: =TRIM(C6911) -> Adam Shankman | E6911: =TRIM(D6911) -> Nikki Blonsky, John Travolta, Michelle Pfeiffer, Christopher Walken, Amanda Bynes, James Marsden, Queen Latifah, Zac Efron, Brittany Snow, Allison Janney, Elijah Kelley, Jerry Stiller | F6911: =TRIM(E6911) -> United States, United Kingdom, Canada | G6911: January 1, 2020 | H6911: 2007 | I6911: PG | J6911: 116 min | K6911: =LEFT(J6911,FIND(" ",J6911)-1) -> 116 | L6911: =RIGHT(J6911,LEN(J6911)-FIND(" ",J6911)) -> min | M6911: Children & Family Movies, Comedies, Music & Musicals | N6911: =TRIM(M6911) -> Children & Family Movies, Comedies, Music & Musicals
A6912: s6911 | B6912: Movie | C6912: =TRIM('4th netflix_titles'!$C6912) -> HALO Legends | D6912: =TRIM(C6912) -> Shinji Aramaki, Mamoru Oshii, Hideki Futamura, Toshiyuki Kanno, Tomoki Kyoda, Koichi Mashimo, Yasushi Muraki, Daisuke Nishio, Frank O'Connor, Koji Sawai, Joseph Chou, Hiroshi Yamazaki | E6912: =TRIM(D6912) -> Andy McAvin, James Faulkner, Luci Christian, John Swasey | F6912: =TRIM(E6912) -> United States, Japan | G6912: May 1, 2017 | H6912: 2009 | I6912: PG-13 | J6912: 117 min | K6912: =LEFT(J6912,FIND(" ",J6912)-1) -> 117 | L6912: =RIGHT(J6912,LEN(J6912)-FIND(" ",J6912)) -> min | M6912: Action & Adventure, Anime Features, Sci-Fi & Fantasy | N6912: =TRIM(M6912) -> Action & Adventure, Anime Features, Sci-Fi & Fantasy
A6913: s6912 | B6913: Movie | C6913: =TRIM('4th netflix_titles'!$C6913) -> Halo: The Fall of Reach | D6913: =TRIM(C6913) -> Ian Kirby | E6913: =TRIM(D6913) -> Jen Taylor, Steve Downes, Michelle Lukes, Britt Baron, Travis Willingham, John Bently, Todd Haberkorn, Cole Jensen | F6913: =TRIM(E6913) -> United States | G6913: March 7, 2016 | H6913: 2015 | I6913: TV-14 | J6913: 65 min | K6913: =LEFT(J6913,FIND(" ",J6913)-1) -> 65 | L6913: =RIGHT(J6913,LEN(J6913)-FIND(" ",J6913)) -> min | M6913: Action & Adventure, Sci-Fi & Fantasy | N6913: =TRIM(M6913) -> Action & Adventure, Sci-Fi & Fantasy
A6914: s6913 | B6914: Movie | C6914: =TRIM('4th netflix_titles'!$C6914) -> Hamara Dil Aapke Paas Hai | D6914: =TRIM(C6914) -> Satish Kaushik | E6914: =TRIM(D6914) -> Anil Kapoor, Aishwarya Rai Bachchan, Sonali Bendre, Puru Rajkumar, Anupam Kher, Satish Kaushik, Mukesh Rishi, Jaspal Bhatti, Razak Khan, Himani Shivpuri, Smita Jaykar, Tanaaz Currim Irani | F6914: =TRIM(E6914) -> India | G6914: March 1, 2018 | H6914: 2000 | I6914: TV-14 | J6914: 158 min | K6914: =LEFT(J6914,FIND(" ",J6914)-1) -> 158 | L6914: =RIGHT(J6914,LEN(J6914)-FIND(" ",J6914)) -> min | M6914: Dramas, International Movies, Music & Musicals | N6914: =TRIM(M6914) -> Dramas, International Movies, Music & Musicals
A6915: s6914 | B6915: Movie | C6915: =TRIM('4th netflix_titles'!$C6915) -> Hamburger Hill | D6915: =TRIM(C6915) -> John Irvin | E6915: =TRIM(D6915) -> Anthony Barille, Michael Boatman, Don Cheadle, Michael Dolan, Don James, Dylan McDermott, Michael A. Nickles, Harry O'Reilly, Daniel O'Shea, Tim Quill, Tommy Swerdlow, Courtney B. Vance, Steven Weber, Tegan West | F6915: =TRIM(E6915) -> United States | G6915: November 23, 2019 | H6915: 1987 | I6915: R | J6915: 110 min | K6915: =LEFT(J6915,FIND(" ",J6915)-1) -> 110 | L6915: =RIGHT(J6915,LEN(J6915)-FIND(" ",J6915)) -> min | M6915: Action & Adventure, Dramas | N6915: =TRIM(M6915) -> Action & Adventure, Dramas
... A7197: s7196 | B7197: Movie | C7197: =TRIM('4th netflix_titles'!$C7197) -> Kidnapping Mr. Heineken | D7197: =TRIM(C7197) -> Daniel Alfredson | E7197: =TRIM(D7197) -> Jim Sturgess, Sam Worthington, Ryan Kwanten, Anthony Hopkins, Mark van Eeuwen, Thomas Cocquerel, Jemima West, David Dencik | F7197: =TRIM(E7197) -> Netherlands, Belgium, United Kingdom, United States | G7197: September 8, 2017 | H7197: 2015 | I7197: R | J7197: 95 min | K7197: =LEFT(J7197,FIND(" ",J7197)-1) -> 95 | L7197: =RIGHT(J7197,LEN(J7197)-FIND(" ",J7197)) -> min | M7197: Action & Adventure, Dramas, International Movies | N7197: =TRIM(M7197) -> Action & Adventure, Dramas, International Movies
A7198: s7197 | B7198: TV Show | C7198: =TRIM('4th netflix_titles'!$C7198) -> Kikoriki | D7198: =TRIM(C7198) -> UNKNOWN | E7198: =TRIM(D7198) -> Igor Dmitriev | F7198: =TRIM(E7198) -> UNKNOWN | H7198: 2010 | I7198: TV-Y | J7198: 2 Seasons | K7198: =LEFT(J7198,FIND(" ",J7198)-1) -> 2 | L7198: =RIGHT(J7198,LEN(J7198)-FIND(" ",J7198)) -> Seasons | M7198: Kids' TV | N7198: =TRIM(M7198) -> Kids' TV
A7199: s7198 | B7199: Movie | C7199: =TRIM('4th netflix_titles'!$C7199) -> Kill Bill: Vol. 1 | D7199: =TRIM(C7199) -> Quentin Tarantino | E7199: =TRIM(D7199) -> Uma Thurman, Lucy Liu, Vivica A. Fox, Daryl Hannah, David Carradine, Michael Madsen, Julie Dreyfus, Chiaki Kuriyama, Sonny Chiba, Gordon Liu | F7199: =TRIM(E7199) -> United States, Japan | G7199: January 1, 2020 | H7199: 2003 | I7199: R | J7199: 111 min | K7199: =LEFT(J7199,FIND(" ",J7199)-1) -> 111 | L7199: =RIGHT(J7199,LEN(J7199)-FIND(" ",J7199)) -> min | M7199: Action & Adventure | N7199: =TRIM(M7199) -> Action & Adventure
A7200: s7199 | B7200: Movie | C7200: =TRIM('4th netflix_titles'!$C7200) -> Kill Bill: Vol. 2 | D7200: =TRIM(C7200) -> Quentin Tarantino | E7200: =TRIM(D7200) -> Uma Thurman, David Carradine, Michael Madsen, Daryl Hannah, Gordon Liu, Michael Parks, Perla Haney-Jardine, Helen Kim, Claire Smithies, Clark Middleton | F7200: =TRIM(E7200) -> United States | G7200: January 1, 2020 | H7200: 2004 | I7200: R | J7200: 137 min | K7200: =LEFT(J7200,FIND(" ",J7200)-1) -> 137 | L7200: =RIGHT(J7200,LEN(J7200)-FIND(" ",J7200)) -> min | M7200: Action & Adventure | N7200: =TRIM(M7200) -> Action & Adventure
A7201: s7200 | B7201: Movie | C7201: =TRIM('4th netflix_titles'!$C7201) -> Kill Command | D7201: =TRIM(C7201) -> Steven Gomez | E7201: =TRIM(D7201) -> Vanessa Kirby, David Ajala, Mike Noble, Bentley Kalu, Tom McKay, Kelly Gough, Osi Okerafor, Damian Kell, Tim Ahern, Deborah Rosan, Thure Lindhardt | F7201: =TRIM(E7201) -> United Kingdom | G7201: February 23, 2017 | H7201: 2016 | I7201: TV-MA | J7201: 100 min | K7201: =LEFT(J7201,FIND(" ",J7201)-1) -> 100 | L7201: =RIGHT(J7201,LEN(J7201)-FIND(" ",J7201)) -> min | M7201: Action & Adventure, Independent Movies, Sci-Fi & Fantasy | N7201: =TRIM(M7201) -> Action & Adventure, Independent Movies, Sci-Fi & Fantasy
A7202: s7201 | B7202: Movie | C7202: =TRIM('4th netflix_titles'!$C7202) -> Kill Hitler! The Luck of the Devil | D7202: =TRIM(C7202) -> FrÃ©dÃ©ric Tonolli | E7202: =TRIM(D7202) -> Jean-Baptiste Marcenac | F7202: =TRIM(E7202) -> France | G7202: May 1, 2019 | H7202: 2015 | I7202: TV-14 | J7202: 53 min | K7202: =LEFT(J7202,FIND(" ",J7202)-1) -> 53 | L7202: =RIGHT(J7202,LEN(J7202)-FIND(" ",J7202)) -> min | M7202: Documentaries, International Movies | N7202: =TRIM(M7202) -> Documentaries, International Movies
A7203: s7202 | B7203: Movie | C7203: =TRIM('4th netflix_titles'!$C7203) -> Kill Ratio | D7203: =TRIM(C7203) -> Paul Tanter | E7203: =TRIM(D7203) -> Tom Hopper, Amy Huberman, Lacy Moore, Brian McGuinness, Luke Pierucci, Nick Dunning | F7203: =TRIM(E7203) -> United States | G7203: February 17, 2017 | H7203: 2016 | I7203: TV-MA | J7203: 87 min | K7203: =LEFT(J7203,FIND(" ",J7203)-1) -> 87 | L7203: =RIGHT(J7203,LEN(J7203)-FIND(" ",J7203)) -> min | M7203: Action & Adventure | N7203: =TRIM(M7203) -> Action & Adventure
A7204: s7203 | B7204: Movie | C7204: =TRIM('4th netflix_titles'!$C7204) -> Kill the Irishman | D7204: =TRIM(C7204) -> Jonathan Hensleigh | E7204: =TRIM(D7204) -> Ray Stevenson, Vincent D'Onofrio, Val Kilmer, Christopher Walken, Linda Cardellini, Fionnula Flanagan, Jason Butler Harner, Vinnie Jones, Paul Sorvino, Marcus Thomas, Tony Darrow | F7204: =TRIM(E7204) -> United States | G7204: August 21, 2020 | H7204: 2011 | I7204: R | J7204: 106 min | K7204: =LEFT(J7204,FIND(" ",J7204)-1) -> 106 | L7204: =RIGHT(J7204,LEN(J7204)-FIND(" ",J7204)) -> min | M7204: Action & Adventure, Dramas, Independent Movies | N7204: =TRIM(M7204) -> Action & Adventure, Dramas, Independent Movies
A7205: s7204 | B7205: Movie | C7205: =TRIM('4th netflix_titles'!$C7205) -> Killer Klowns from Outer Space | D7205: =TRIM(C7205) -> Stephen Chiodo | E7205: =TRIM(D7205) -> Grant Cramer, Suzanne Snyder, John Allen Nelson, John Vernon, Michael S. Siegel, Peter Licassi, Royal Dano, Christopher Titus, Irene Michaels, Karla Sue Krull | F7205: =TRIM(E7205) -> United States | G7205: April 1, 2020 | H7205: 1988 | I7205: PG-13 | J7205: 86 min | K7205: =LEFT(J7205,FIND(" ",J7205)-1) -> 86 | L7205: =RIGHT(J7205,LEN(J7205)-FIND(" ",J7205)) -> min | M7205: Comedies, Cult Movies, Horror Movies | N7205: =TRIM(M7205) -> Comedies, Cult Movies, Horror Movies
A7206: s7205 | B7206: Movie | C7206: =TRIM('4th netflix_titles'!$C7206) -> Killers | D7206: =TRIM(C7206) -> Robert Luketic | E7206: =TRIM(D7206) -> Katherine Heigl, Ashton Kutcher, Tom Selleck, Catherine O'Hara, Katheryn Winnick, Kevin Sussman, Lisa Ann Walter, Casey Wilson, Rob Riggle, Martin Mull, Alex Borstein | F7206: =TRIM(E7206) -> United States | G7206: January 1, 2021 | H7206: 2010 | I7206: PG-13 | J7206: 100 min | K7206: =LEFT(J7206,FIND(" ",J7206)-1) -> 100 | L7206: =RIGHT(J7206,LEN(J7206)-FIND(" ",J7206)) -> min | M7206: Action & Adventure, Comedies, Romantic Movies | N7206: =TRIM(M7206) -> Action & Adventure, Comedies, Romantic Movies
A7207: s7206 | B7207: Movie | C7207: =TRIM('4th netflix_titles'!$C7207) -> Kills on Wheels | D7207: =TRIM(C7207) -> Attila Till | E7207: =TRIM(D7207) -> Szabolcs ThurÃ³czy, ZoltÃ¡n Fenyvesi, AdÃ¡m Fekete, Dusan Vitanovic, MÃ³nika Balsai, Lidia Danis, ZoltÃ¡n Mucsi | F7207: =TRIM(E7207) -> Hungary | G7207: March 15, 2018 | H7207: 2016 | I7207: TV-MA | J7207: 103 min | K7207: =LEFT(J7207,FIND(" ",J7207)-1) -> 103 | L7207: =RIGHT(J7207,LEN(J7207)-FIND(" ",J7207)) -> min | M7207: Action & Adventure, Dramas, International Movies | N7207: =TRIM(M7207) -> Action & Adventure, Dramas, International Movies
A7208: s7207 | B7208: Movie | C7208: =TRIM('4th netflix_titles'!$C7208) -> Kilo Two Bravo | D7208: =TRIM(C7208) -> Paul Katis | E7208: =TRIM(D7208) -> David Elliot, Mark Stanley, Scott Kyle, Benjamin O'Mahony, Bryan Parry, Liam Ainsworth, Andy Gibbins, John Doughty, Paul Luebke, Thomas Davison, Grant Kilburn, Robert Mitchell, Jon-Paul Bell, Malachi Kirby, Ali Cook | F7208: =TRIM(E7208) -> United Kingdom | G7208: March 1, 2019 | H7208: 2014 | I7208: R | J7208: 109 min | K7208: =LEFT(J7208,FIND(" ",J7208)-1) -> 109 | L7208: =RIGHT(J7208,LEN(J7208)-FIND(" ",J7208)) -> min | M7208: Dramas, Independent Movies, Thrillers | N7208: =TRIM(M7208) -> Dramas, Independent Movies, Thrillers
A7209: s7208 | B7209: Movie | C7209: =TRIM('4th netflix_titles'!$C7209) -> King Jack | D7209: =TRIM(C7209) -> Felix Thompson | E7209: =TRIM(D7209) -> Charlie Plummer, Cory Nichols, Christian Madsen, Danny Flaherty, Erin Davie, Chloe Levine | F7209: =TRIM(E7209) -> United States | G7209: July 1, 2016 | H7209: 2015 | I7209: NR | J7209: 81 min | K7209: =LEFT(J7209,FIND(" ",J7209)-1) -> 81 | L7209: =RIGHT(J7209,LEN(J7209)-FIND(" ",J7209)) -> min | M7209: Dramas, Independent Movies | N7209: =TRIM(M7209) -> Dramas, Independent Movies
A7210: s7209 | B7210: Movie | C7210: =TRIM('4th netflix_titles'!$C7210) -> King's Ransom | D7210: =TRIM(C7210) -> Jeffrey W. Byrd | E7210: =TRIM(D7210) -> Anthony Anderson, Jay Mohr, Kellita Smith, Nicole Ari Parker, Regina Hall, Loretta Devine, Donald Faison, Leila Arcieri, Charlie Murphy, Brooke D'Orsay | F7210: =TRIM(E7210) -> United States, Canada | G7210: November 1, 2019 | H7210: 2005 | I7210: PG-13 | J7210: 98 min | K7210: =LEFT(J7210,FIND(" ",J7210)-1) -> 98 | L7210: =RIGHT(J7210,LEN(J7210)-FIND(" ",J7210)) -> min | M7210: Action & Adventure, Comedies | N7210: =TRIM(M7210) -> Action & Adventure, Comedies
... A7255: s7254 | B7255: Movie | C7255: =TRIM('4th netflix_titles'!$C7255) -> La Coppia dei Campioni | D7255: =TRIM(C7255) -> Giulio Base | E7255: =TRIM(D7255) -> Massimo Boldi, Massimiliano Tortora, Anna Maria Barbera, Massimo Ceccherini, Pia Lanciotti, Flora Canto | F7255: =TRIM(E7255) -> Italy | G7255: February 15, 2017 | H7255: 2016 | I7255: TV-MA | J7255: 88 min | K7255: =LEFT(J7255,FIND(" ",J7255)-1) -> 88 | L7255: =RIGHT(J7255,LEN(J7255)-FIND(" ",J7255)) -> min | M7255: Comedies, International Movies | N7255: =TRIM(M7255) -> Comedies, International Movies
A7256: s7255 | B7256: TV Show | C7256: =TRIM('4th netflix_titles'!$C7256) -> La Familia P. Luche | D7256: =TRIM(C7256) -> UNKNOWN | E7256: =TRIM(D7256) -> Eugenio Derbez, Consuelo Duval, Luis Manuel Ãvila, Regina BlandÃ³n, Miguel Perez, Barbara Torres, Dalilah Polanco, Pierre Angelo | F7256: =TRIM(E7256) -> United States | H7256: 2012 | I7256: TV-14 | J7256: 3 Seasons | K7256: =LEFT(J7256,FIND(" ",J7256)-1) -> 3 | L7256: =RIGHT(J7256,LEN(J7256)-FIND(" ",J7256)) -> Seasons | M7256: International TV Shows, Spanish-Language TV Shows, TV Comedies | N7256: =TRIM(M7256) -> International TV Shows, Spanish-Language TV Shows, TV Comedies
A7257: s7256 | B7257: TV Show | C7257: =TRIM('4th netflix_titles'!$C7257) -> La Femme | D7257: =TRIM(C7257) -> UNKNOWN | E7257: =TRIM(D7257) -> Zoe Tay, Ann Kok, Tiffany Leong, Tay Ping Hui, Yao Wenlong, Shaun Chen, Paige Chua, Nat Ho, Desmond Sim | F7257: =TRIM(E7257) -> UNKNOWN | G7257: October 16, 2017 | H7257: 2016 | I7257: TV-14 | J7257: 1 Season | K7257: =LEFT(J7257,FIND(" ",J7257)-1) -> 1 | L7257: =RIGHT(J7257,LEN(J7257)-FIND(" ",J7257)) -> Season | M7257: International TV Shows, TV Dramas | N7257: =TRIM(M7257) -> International TV Shows, TV Dramas
A7258: s7257 | B7258: TV Show | C7258: =TRIM('4th netflix_titles'!$C7258) -> La Piloto | D7258: =TRIM(C7258) -> UNKNOWN | E7258: =TRIM(D7258) -> Livia Brito, Juan Eduardo Colucho, Arap Bethke, MarÃ­a Fernanda YÃ©pes, Alejandro Nones, MarÃ­a De La Fuente, VerÃ³nica Montes, Natasha DomÃ­nguez, MarÃ­a Fernanda GarcÃ­a, Mauricio Aspe, Stephanie Salas, Tommy Vasquez, Macarena Achaga | F7258: =TRIM(E7258) -> Mexico | G7258: April 2, 2018 | H7258: 2017 | I7258: TV-MA | J7258: 1 Season | K7258: =LEFT(J7258,FIND(" ",J7258)-1) -> 1 | L7258: =RIGHT(J7258,LEN(J7258)-FIND(" ",J7258)) -> Season | M7258: Crime TV Shows, International TV Shows, Spanish-Language TV Shows | N7258: =TRIM(M7258) -> Crime TV Shows, International TV Shows, Spanish-Language TV Shows
A7259: s7258 | B7259: TV Show | C7259: =TRIM('4th netflix_titles'!$C7259) -> La Rosa de Guadalupe | D7259: =TRIM(C7259) -> UNKNOWN | E7259: =TRIM(D7259) -> Milia Nader, Francisco AvendaÃ±o, Diego Lara, Sandra Itzel, Marisol del Olmo, Aleyda Gallardo, Gerardo MurguÃ­a, Roxana Saucedo, Emmanuel Orenday, Maru DueÃ±as | F7259: =TRIM(E7259) -> Mexico | G7259: January 15, 2019 | H7259: 2010 | I7259: TV-PG | J7259: 1 Season | K7259: =LEFT(J7259,FIND(" ",J7259)-1) -> 1 | L7259: =RIGHT(J7259,LEN(J7259)-FIND(" ",J7259)) -> Season | M7259: Classic & Cult TV, Crime TV Shows, International TV Shows | N7259: =TRIM(M7259) -> Classic & Cult TV, Crime TV Shows, International TV Shows
A7260: s7259 | B7260: TV Show | C7260: =TRIM('4th netflix_titles'!$C7260) -> La Viuda Negra | D7260: =TRIM(C7260) -> Alejandro Lozano | E7260: =TRIM(D7260) -> Ana Serradilla, JuliÃ¡n RomÃ¡n, Ramiro Meneses, Juan Pablo Gamboa, Eileen Moreno, Luis Alfredo Velasco, Margarita Reyes, Alexander Gil, Luis Roberto GuzmÃ¡n, RaÃºl MÃ©ndez | F7260: =TRIM(E7260) -> Colombia, Mexico, United States | G7260: January 15, 2019 | H7260: 2016 | I7260: TV-14 | J7260: 1 Season | K7260: =LEFT(J7260,FIND(" ",J7260)-1) -> 1 | L7260: =RIGHT(J7260,LEN(J7260)-FIND(" ",J7260)) -> Season | M7260: Crime TV Shows, International TV Shows, Spanish-Language TV Shows | N7260: =TRIM(M7260) -> Crime TV Shows, International TV Shows, Spanish-Language TV Shows
...
